MANIFEST.in
README.md
setup.py
django_shop_richproduct.egg-info/PKG-INFO
django_shop_richproduct.egg-info/SOURCES.txt
django_shop_richproduct.egg-info/dependency_links.txt
django_shop_richproduct.egg-info/not-zip-safe
django_shop_richproduct.egg-info/requires.txt
django_shop_richproduct.egg-info/top_level.txt
requirements/common.txt
requirements/development.txt
requirements/production.txt
requirements/testing.txt
shop_richproduct/__init__.py
shop_richproduct/models.py
shop_richproduct/migrations/0001_initial.py
shop_richproduct/migrations/0002_richproduct_purchase_button_label.py
shop_richproduct/migrations/__init__.py
shop_richproduct/south_migrations/0001_initial.py
shop_richproduct/south_migrations/0002_auto__add_field_richproduct_description_placeholder.py
shop_richproduct/south_migrations/__init__.py
shop_richproduct/templates/product/product_detail.html
shop_richproduct/templates/product/product_list.html
shop_richproduct/templates/shop/product_list.html