Metadata-Version: 1.0
Name: django-shop-richproduct
Version: 1.1.0
Summary: Rich product functionality for django shop.
Home-page: UNKNOWN
Author: Nimbis Services, Inc.
Author-email: info@nimbisservices.com
License: BSD
Platform: UNKNOWN
